py_rdpackages/__init__.py
py_rdpackages/rdpackages.py
py_rdpackages-1.0.3.dist-info/LICENSE.md
py_rdpackages-1.0.3.dist-info/METADATA
py_rdpackages-1.0.3.dist-info/WHEEL
py_rdpackages-1.0.3.dist-info/top_level.txt
py_rdpackages-1.0.3.dist-info/RECORD
