Metadata-Version: 2.1
Name: py-rdpackages
Version: 1.0.3
Summary: A Pythonic Package for Regression Discontinuity
Home-page: https://github.com/lucashusted/py_rdpackages
Author: Lucas Husted
Author-email: lucas.f.husted@columbia.edu
License: GNU
Platform: UNKNOWN
Classifier: Development Status :: 3 - Alpha
Classifier: Intended Audience :: End Users/Desktop
Classifier: Intended Audience :: Financial and Insurance Industry
Classifier: Intended Audience :: Science/Research
Classifier: Programming Language :: Python :: 3.6
Classifier: Programming Language :: Python :: 3.7
Classifier: Programming Language :: Python :: 3.8
Classifier: Operating System :: MacOS :: MacOS X
Classifier: Operating System :: Microsoft :: Windows
Classifier: Operating System :: POSIX
Classifier: Programming Language :: Python
Classifier: Programming Language :: R
Requires-Python: >=3
Requires-Dist: matplotlib
Requires-Dist: seaborn
Requires-Dist: rpy2 (<2.9.5)
Requires-Dist: numpy
Requires-Dist: pandas (>=0.25)
Requires-Dist: patsy
Requires-Dist: tzlocal
